{
  "version": "7",
  "dialect": "postgresql",
  "entries": [
    {
      "idx": 0,
      "version": "7",
      "when": 1773386552757,
      "tag": "0000_burly_la_nuit",
      "breakpoints": true
    },
    {
      "idx": 1,
      "version": "7",
      "when": 1773817521667,
      "tag": "0001_dark_wendell_rand",
      "breakpoints": true
    },
    {
      "idx": 2,
      "version": "7",
      "when": 1774119961268,
      "tag": "0002_hesitant_oracle",
      "breakpoints": true
    },
    {
      "idx": 3,
      "version": "7",
      "when": 1774184879710,
      "tag": "0003_mushy_rogue",
      "breakpoints": true
    }
  ]
}